[
  {
    "question": "What is the time complexity of binary search on a sorted array?",
    "choices": {
      "a": "O(n)",
      "b": "O(log n)",
      "c": "O(n log n)",
      "d": "O(1)"
    },
    "answer": "b"
  },
  {
    "question": "Which of the following is not a programming paradigm?",
    "choices": {
      "a": "Object-Oriented",
      "b": "Functional",
      "c": "Procedural",
      "d": "Syntax-Based"
    },
    "answer": "d"
  },
  {
    "question": "In an undirected graph, which of the following statements is true?",
    "choices": {
      "a": "The sum of all vertex degrees is equal to the number of vertices.",
      "b": "The number of edges is always even.",
      "c": "The sum of all vertex degrees is twice the number of edges.",
      "d": "All vertices must have the same degree."
    },
    "answer": "c"
  },
  {
    "question": "Which data structure is typically used to implement a priority queue?",
    "choices": {
      "a": "Stack",
      "b": "Queue",
      "c": "Heap",
      "d": "Linked List"
    },
    "answer": "c"
  },
  {
    "question": "Which sorting algorithm has the best average case time complexity?",
    "choices": {
      "a": "Bubble Sort",
      "b": "Merge Sort",
      "c": "Selection Sort",
      "d": "Insertion Sort"
    },
    "answer": "b"
  }
]
